{"index.md":"Bi15vU2v","page.md":"DHM3c4vS","page_1.md":"a52JPnJH","page_2.md":"bp0jmjul","page_index.md":"t9B1bATo","pages_about.md":"CwZ2ZA8A","pages_archives.md":"DtzH50fw","pages_categories.md":"DxGDtKu3","pages_categories_和ta的日常.md":"BCIv9FK6","pages_categories_存档处.md":"HaiPLldv","pages_categories_碎碎念.md":"CEkLIQO9","pages_categories_胡思乱想.md":"DFqOafls","pages_index.md":"DO0n6Jru","pages_statistics.md":"CKbryqCf","pages_tags.md":"HFYkc01q","pages_tags_blog.md":"BNkPB_wN","pages_tags_markdown.md":"BsMLTb87","pages_tags_价值观.md":"D2_bCyT1","pages_tags_吐槽.md":"d2LwNhwz","pages_tags_哲学.md":"CzRn_B9L","pages_tags_大事记.md":"Bi_a8wlp","pages_tags_实践.md":"Wnqn-rf5","pages_tags_小露.md":"Cr2rcXIn","pages_tags_意格.md":"B1DvCYut","pages_tags_指南.md":"FLHOGlgs","pages_tags_设定.md":"mBvqNRYF","pages_timeline.md":"DyJ0sC9m","posts_2025_0001.md":"X2Yg4mkz","posts_2025_0002.md":"hbV9x70S","posts_2025_0003.md":"BW-_SWsv","posts_2025_0004.md":"DahZbZmz","posts_2025_0005.md":"By77JHqW","posts_2025_0006.md":"BK_joR7l","posts_2025_0007.md":"CPvKCp1g","posts_2025_0008.md":"BqAt4R7q","posts_2025_0009.md":"DSooYJAa","posts_2025_0010.md":"Ca4OXkF0","posts_2025_0011.md":"vj-uFQa4","posts_2025_0012.md":"D1he3tMM","posts_2025_0013.md":"BdhGGZHR"}
